{
  "name": "Adium",
  "slug": "adium",
  "description": "Free instant messaging client supporting multiple protocols",
  "website": "https://adium.im",
  "platform": "macOS",
  "architecture": "universal",
  "min_os": "10.10",
  "auto_updates": false,
  "version_check": {
    "method": "sparkle_rss",
    "url": "https://www.adium.im/sparkle/update.php",
    "extraction": {
      "type": "sparkle_xml",
      "version_field": "sparkle:version on enclosure",
      "example": "1.5.10.4"
    },
    "headers": {}
  },
  "download": {
    "method": "construct_url",
    "pattern": "https://adiumx.cachefly.net/Adium_{VERSION}.dmg",
    "file_type": "dmg",
    "headers": {}
  },
  "changelog": {
    "method": "construct_url",
    "pattern": "https://www.adium.im/changelogs/{VERSION}.html"
  },
  "release_date": {
    "method": "local_plist",
    "note": "AIBuildDate field in Info.plist (Unix timestamp). Sparkle pubDate is often empty."
  },
  "notes": "*** PROJECT ABANDONED ***. Last release 1.5.10.4 (2017-04-27). The Sparkle feed at update.php is stale \u2014 only contains v1.1.4. Original sparkle.adium.im/appcast.xml returns 404. No functional auto-update. Profile retained for installed-version reporting only.",
  "last_updated": "2026-06-21",
  "$schema": "https://raw.githubusercontent.com/evenwebb/macupdater-profiles/main/schema.json",
  "category": "messaging",
  "license": "free",
  "skip": true
}
